boards/__init__.py
boards/cli.py
boards/config.py
boards/logging.py
boards/middleware.py
boards/py.typed
boards/redis_pool.py
boards/tenant_isolation.py
boards/validation.py
boards/api/app.py
boards/api/auth.py
boards/api/otel.py
boards/api/endpoints/__init__.py
boards/api/endpoints/jobs.py
boards/api/endpoints/setup.py
boards/api/endpoints/sse.py
boards/api/endpoints/storage.py
boards/api/endpoints/tenant_registration.py
boards/api/endpoints/uploads.py
boards/api/endpoints/webhooks.py
boards/auth/__init__.py
boards/auth/context.py
boards/auth/factory.py
boards/auth/middleware.py
boards/auth/provisioning.py
boards/auth/tenant_extraction.py
boards/auth/adapters/__init__.py
boards/auth/adapters/auth0.py
boards/auth/adapters/base.py
boards/auth/adapters/clerk.py
boards/auth/adapters/jwt.py
boards/auth/adapters/none.py
boards/auth/adapters/oidc.py
boards/auth/adapters/supabase.py
boards/database/__init__.py
boards/database/cli.py
boards/database/connection.py
boards/database/models.py
boards/database/seed_data.py
boards/dbmodels/__init__.py
boards/generators/__init__.py
boards/generators/artifact_resolution.py
boards/generators/artifacts.py
boards/generators/base.py
boards/generators/loader.py
boards/generators/registry.py
boards/generators/resolution.py
boards/generators/implementations/__init__.py
boards/generators/implementations/fal/__init__.py
boards/generators/implementations/fal/utils.py
boards/generators/implementations/fal/audio/__init__.py
boards/generators/implementations/fal/audio/beatoven_music_generation.py
boards/generators/implementations/fal/audio/beatoven_sound_effect_generation.py
boards/generators/implementations/fal/audio/chatterbox_text_to_speech.py
boards/generators/implementations/fal/audio/chatterbox_tts_turbo.py
boards/generators/implementations/fal/audio/elevenlabs_sound_effects_v2.py
boards/generators/implementations/fal/audio/elevenlabs_tts_eleven_v3.py
boards/generators/implementations/fal/audio/fal_elevenlabs_tts_turbo_v2_5.py
weirdfingers_boards-0.11.3.dist-info/METADATA
weirdfingers_boards-0.11.3.dist-info/WHEEL
weirdfingers_boards-0.11.3.dist-info/entry_points.txt
weirdfingers_boards-0.11.3.dist-info/top_level.txt
weirdfingers_boards-0.11.3.dist-info/RECORD
