Metadata-Version: 2.4
Name: weirdfingers-boards
Version: 0.11.3
Summary: Backend API server for Boards - AI creative toolkit with GraphQL, auth adapters, and generation workers
Author-email: Boards Contributors <ai.overlord@weirdfingers.com>
License: MIT
Project-URL: Homepage, https://github.com/weirdfingers/boards
Project-URL: Documentation, https://docs.boards.io
Project-URL: Repository, https://github.com/weirdfingers/boards
Project-URL: Issues, https://github.com/weirdfingers/boards/issues
Project-URL: Changelog, https://github.com/weirdfingers/boards/blob/main/CHANGELOG.md
Keywords: ai,creative,toolkit,graphql,fastapi,strawberry,auth,generation
Classifier: Development Status :: 3 - Alpha
Classifier: Intended Audience :: Developers
Classifier: License :: OSI Approved :: MIT License
Classifier: Programming Language :: Python :: 3
Classifier: Programming Language :: Python :: 3.12
Classifier: Topic :: Internet :: WWW/HTTP :: HTTP Servers
Classifier: Topic :: Software Development :: Libraries :: Application Frameworks
Classifier: Topic :: Scientific/Engineering :: Artificial Intelligence
Classifier: Framework :: FastAPI
Classifier: Framework :: AsyncIO
Requires-Python: >=3.12
Requires-Dist: sqlalchemy>=2.0.0
Requires-Dist: pydantic>=2.0.0
Requires-Dist: pydantic-settings>=2.0.0
Requires-Dist: httpx[http2]>=0.24.0
Requires-Dist: python-dotenv>=1.0.0
Requires-Dist: strawberry-graphql[fastapi,opentelemetry]>=0.200.0
Requires-Dist: fastapi>=0.100.0
Requires-Dist: uvicorn[standard]>=0.23.0
Requires-Dist: dramatiq[redis,watch]>=1.15.0
Requires-Dist: pillow>=10.0.0
Requires-Dist: numpy>=1.24.0
Requires-Dist: psycopg[binary]>=3.1.0
Requires-Dist: structlog>=23.0.0
Requires-Dist: asyncpg>=0.29.0
Requires-Dist: alembic>=1.13.2
Requires-Dist: aiofiles>=23.0.0
Requires-Dist: pyyaml>=6.0.0
Requires-Dist: click>=8.0.0
Requires-Dist: redis>=5.0.0
Requires-Dist: pyjwt[crypto]>=2.8.0
Requires-Dist: psutil>=7.0.0
Requires-Dist: opentelemetry-api>=1.20.0
Requires-Dist: opentelemetry-sdk>=1.20.0
Requires-Dist: opentelemetry-exporter-gcp-trace>=1.6.0
Requires-Dist: opentelemetry-exporter-otlp-proto-grpc>=1.20.0
Requires-Dist: opentelemetry-instrumentation-fastapi>=0.40.0
Requires-Dist: opentelemetry-instrumentation-sqlalchemy>=0.40.0
Requires-Dist: opentelemetry-instrumentation-asyncpg>=0.40.0
Requires-Dist: opentelemetry-instrumentation-httpx>=0.40.0
Provides-Extra: generators-replicate
Requires-Dist: replicate>=1.0.4; extra == "generators-replicate"
Provides-Extra: generators-openai
Requires-Dist: openai>=1.60.1; extra == "generators-openai"
Provides-Extra: generators-fal
Requires-Dist: fal-client>=0.5.0; extra == "generators-fal"
Provides-Extra: generators-anthropic
Requires-Dist: anthropic>=0.25.0; extra == "generators-anthropic"
Provides-Extra: generators-together
Requires-Dist: together>=1.0.0; extra == "generators-together"
Provides-Extra: generators-all
Requires-Dist: replicate>=1.0.4; extra == "generators-all"
Requires-Dist: openai>=1.60.1; extra == "generators-all"
Requires-Dist: fal-client>=0.5.0; extra == "generators-all"
Requires-Dist: anthropic>=0.25.0; extra == "generators-all"
Requires-Dist: together>=1.0.0; extra == "generators-all"
Provides-Extra: storage-supabase
Requires-Dist: supabase>=2.0.0; extra == "storage-supabase"
Provides-Extra: storage-s3
Requires-Dist: boto3>=1.34.0; extra == "storage-s3"
Requires-Dist: aioboto3>=12.0.0; extra == "storage-s3"
Provides-Extra: storage-gcs
Requires-Dist: google-cloud-storage>=2.10.0; extra == "storage-gcs"
Provides-Extra: storage-all
Requires-Dist: supabase>=2.0.0; extra == "storage-all"
Requires-Dist: boto3>=1.34.0; extra == "storage-all"
Requires-Dist: aioboto3>=12.0.0; extra == "storage-all"
Requires-Dist: google-cloud-storage>=2.10.0; extra == "storage-all"
Provides-Extra: auth-supabase
Requires-Dist: supabase>=2.0.0; extra == "auth-supabase"
Provides-Extra: all
Requires-Dist: replicate>=1.0.4; extra == "all"
Requires-Dist: openai>=1.60.1; extra == "all"
Requires-Dist: fal-client>=0.5.0; extra == "all"
Requires-Dist: anthropic>=0.25.0; extra == "all"
Requires-Dist: together>=1.0.0; extra == "all"
Requires-Dist: supabase>=2.0.0; extra == "all"
Requires-Dist: boto3>=1.34.0; extra == "all"
Requires-Dist: aioboto3>=12.0.0; extra == "all"
Requires-Dist: google-cloud-storage>=2.10.0; extra == "all"
Provides-Extra: dev
Requires-Dist: pytest>=7.0.0; extra == "dev"
Requires-Dist: pytest-asyncio>=0.21.0; extra == "dev"
Requires-Dist: pytest-postgresql>=6.0.0; extra == "dev"
Requires-Dist: pytest-cov>=4.0.0; extra == "dev"
Requires-Dist: ruff>=0.1.0; extra == "dev"
Requires-Dist: pyright>=1.1.0; extra == "dev"
Requires-Dist: black>=23.0.0; extra == "dev"
Requires-Dist: pre-commit>=3.0.0; extra == "dev"
Requires-Dist: openai>=1.60.1; extra == "dev"
Requires-Dist: anthropic>=0.25.0; extra == "dev"
Requires-Dist: replicate>=1.0.4; extra == "dev"
Requires-Dist: together>=1.0.0; extra == "dev"
Requires-Dist: fal-client>=0.5.0; extra == "dev"
Requires-Dist: supabase>=2.0.0; extra == "dev"
Requires-Dist: boto3>=1.34.0; extra == "dev"
Requires-Dist: aioboto3>=12.0.0; extra == "dev"
Requires-Dist: google-cloud-storage>=2.10.0; extra == "dev"
Requires-Dist: types-redis>=4.6.0; extra == "dev"
